setup.py
cart_project/models.py
egen111222_cart_project.egg-info/PKG-INFO
egen111222_cart_project.egg-info/SOURCES.txt
egen111222_cart_project.egg-info/dependency_links.txt
egen111222_cart_project.egg-info/top_level.txt