Metadata-Version: 2.1
Name: egen111222-cart-project
Version: 1.0
Summary: Корзина для магазину
Author: Kirill
Author-email: egen13@ukr.net
